SimpleCrypt_Tools-0.2.1.dist-info/DESCRIPTION.rst
SimpleCrypt_Tools-0.2.1.dist-info/METADATA
SimpleCrypt_Tools-0.2.1.dist-info/RECORD
SimpleCrypt_Tools-0.2.1.dist-info/WHEEL
SimpleCrypt_Tools-0.2.1.dist-info/metadata.json
SimpleCrypt_Tools-0.2.1.dist-info/top_level.txt
simplecrypttools/__init__.py
